flask_fixture/__init__.py
flask_fixture/errors.py
flask_fixture/fixture.py
flask_fixture/py.typed
flask_fixture/runner.py
flask_fixture/dataclasses/__init__.py
flask_fixture/dataclasses/output_chunk.py
flask_fixture/dataclasses/route_item.py
flask_fixture/dataclasses/running_startup_result.py
flask_fixture/decorators/__init__.py
flask_fixture/decorators/decorator_config.py
flask_fixture/decorators/decorator_endpoint.py
flask_fixture/logging/__init__.py
flask_fixture/logging/listener.py
flask_fixture/logging/queue_handler.py
flask_fixture/protocols/__init__.py
flask_fixture/protocols/queue.py
flask_fixture/state_storage/__init__.py
flask_fixture/state_storage/collection_of_configs.py
flask_fixture/state_storage/collection_of_importing_modules.py
flask_fixture/state_storage/collection_of_routes.py
flask_fixture-0.0.7.dist-info/LICENSE
flask_fixture-0.0.7.dist-info/METADATA
flask_fixture-0.0.7.dist-info/WHEEL
flask_fixture-0.0.7.dist-info/entry_points.txt
flask_fixture-0.0.7.dist-info/top_level.txt
flask_fixture-0.0.7.dist-info/RECORD
